toncli/__init__.py
toncli/config.ini
toncli/main.py
toncli/lib/fift-libs/Asm.fif
toncli/lib/fift-libs/Color.fif
toncli/lib/fift-libs/Fift.fif
toncli/lib/fift-libs/GetOpt.fif
toncli/lib/fift-libs/Lisp.fif
toncli/lib/fift-libs/Lists.fif
toncli/lib/fift-libs/Stack.fif
toncli/lib/fift-libs/TonUtil.fif
toncli/lib/func-libs/stdlib.func
toncli/modules/__init__.py
toncli/modules/deploy_contract.py
toncli/modules/deploy_wallet_contract.py
toncli/modules/projects.py
toncli/modules/abstract/__init__.py
toncli/modules/abstract/deployer.py
toncli/modules/fift/cli.fif.template
toncli/modules/fift/contract_manipulation.fif
toncli/modules/fift/data_proxy.fif.template
toncli/modules/fift/deploy-wallet.fif
toncli/modules/fift/get_run.fif.template
toncli/modules/fift/run_test.fif.template
toncli/modules/fift/transaction_debug.fif.template
toncli/modules/utils/__init__.py
toncli/modules/utils/check_hash.py
toncli/modules/utils/transaction.py
toncli/modules/utils/fift/__init__.py
toncli/modules/utils/fift/cli_lib.py
toncli/modules/utils/fift/commands.py
toncli/modules/utils/fift/fift.py
toncli/modules/utils/func/__init__.py
toncli/modules/utils/func/commands.py
toncli/modules/utils/func/func.py
toncli/modules/utils/lite_client/__init__.py
toncli/modules/utils/lite_client/commands.py
toncli/modules/utils/lite_client/lite_client.py
toncli/modules/utils/lite_client/parser.py
toncli/modules/utils/system/__init__.py
toncli/modules/utils/system/argparse_fix.py
toncli/modules/utils/system/check_executable.py
toncli/modules/utils/system/conf.py
toncli/modules/utils/system/log.py
toncli/modules/utils/system/project.py
toncli/modules/utils/system/project_conf.py
toncli/modules/utils/ton/cell.py
toncli/projects/external_code/.gitignore
toncli/projects/external_code/README.md
toncli/projects/external_code/build/.gitkeep
toncli/projects/external_code/build/boc/.gitkeep
toncli/projects/external_code/build/boc/c3.boc
toncli/projects/external_code/build/boc/c4.boc
toncli_win-0.0.4.dist-info/LICENSE
toncli_win-0.0.4.dist-info/METADATA
toncli_win-0.0.4.dist-info/WHEEL
toncli_win-0.0.4.dist-info/entry_points.txt
toncli_win-0.0.4.dist-info/top_level.txt
toncli_win-0.0.4.dist-info/RECORD
